{
	"result": 0,
	"success": true,
	"data": {
		"notes": [{
			"liked": false,
			"id": "5cfef0390000000028027c4a",
			"title": "女生必备的10支口红\uD83D\uDC84高级显白，你有几支？？",
			"desc": "最近小红书上口红分享爆火\uD83D\uDD25，很多小姐姐秀出自己认为必入的口红list‼️ 趁着小红书周年起66的时候终于吧最后一支空管",
			"type": "normal",
			"user": {
				"images": "https://img.xiaohongshu.com/avatar/5cd2fa109fb61c000110b64a.jpg@80w_80h_90q_1e_1c_1x.jpg",
				"nickname": "卷毛小狮子",
				"red_official_verified": false,
				"red_official_verify_type": 0,
				"userid": "5cd17b9e000000001202d008"
			},
			"image_info": {
				"fileid": "7708525f-61f2-39b5-809e-21b7da9d9f88",
				"height": 1280,
				"width": 960,
				"url": "http://ci.xiaohongshu.com/7708525f-61f2-39b5-809e-21b7da9d9f88?imageView2/2/w/540/format/jpg",
				"original": "http://ci.xiaohongshu.com/7708525f-61f2-39b5-809e-21b7da9d9f88",
				"index": 0,
				"url_size_large": "http://ci.xiaohongshu.com/7708525f-61f2-39b5-809e-21b7da9d9f88?imageView2/2/w/1080/format/jpg"
			},
			"liked_count": 3451,
			"tag_info": {},
			"images_list": [{
				"fileid": "7708525f-61f2-39b5-809e-21b7da9d9f88",
				"height": 1280,
				"width": 960,
				"url": "http://ci.xiaohongshu.com/7708525f-61f2-39b5-809e-21b7da9d9f88?imageView2/2/w/540/format/jpg",
				"original": "http://ci.xiaohongshu.com/7708525f-61f2-39b5-809e-21b7da9d9f88",
				"index": 0,
				"url_size_large": "http://ci.xiaohongshu.com/7708525f-61f2-39b5-809e-21b7da9d9f88?imageView2/2/w/1080/format/jpg"
			}, {
				"fileid": "906f2f48-b954-394a-8d96-fe0b641120cf",
				"height": 800,
				"width": 600,
				"url": "http://ci.xiaohongshu.com/906f2f48-b954-394a-8d96-fe0b641120cf?imageView2/2/w/540/format/jpg",
				"original": "http://ci.xiaohongshu.com/906f2f48-b954-394a-8d96-fe0b641120cf",
				"url_size_large": "http://ci.xiaohongshu.com/906f2f48-b954-394a-8d96-fe0b641120cf?imageView2/2/w/1080/format/jpg"
			}, {
				"fileid": "65b98182-6b43-3fad-8309-0264e63f50af",
				"height": 800,
				"width": 600,
				"url": "http://ci.xiaohongshu.com/65b98182-6b43-3fad-8309-0264e63f50af?imageView2/2/w/540/format/jpg",
				"original": "http://ci.xiaohongshu.com/65b98182-6b43-3fad-8309-0264e63f50af",
				"url_size_large": "http://ci.xiaohongshu.com/65b98182-6b43-3fad-8309-0264e63f50af?imageView2/2/w/1080/format/jpg"
			}, {
				"fileid": "9a4a1874-d626-338a-bb11-c5d335be58f0",
				"height": 800,
				"width": 600,
				"url": "http://ci.xiaohongshu.com/9a4a1874-d626-338a-bb11-c5d335be58f0?imageView2/2/w/540/format/jpg",
				"original": "http://ci.xiaohongshu.com/9a4a1874-d626-338a-bb11-c5d335be58f0",
				"url_size_large": "http://ci.xiaohongshu.com/9a4a1874-d626-338a-bb11-c5d335be58f0?imageView2/2/w/1080/format/jpg"
			}, {
				"fileid": "f06d8ffd-8020-3aab-9c18-f14f5b936c03",
				"height": 1280,
				"width": 960,
				"url": "http://ci.xiaohongshu.com/f06d8ffd-8020-3aab-9c18-f14f5b936c03?imageView2/2/w/540/format/jpg",
				"original": "http://ci.xiaohongshu.com/f06d8ffd-8020-3aab-9c18-f14f5b936c03",
				"url_size_large": "http://ci.xiaohongshu.com/f06d8ffd-8020-3aab-9c18-f14f5b936c03?imageView2/2/w/1080/format/jpg"
			}, {
				"fileid": "c31f8a4b-4cae-3d34-8be5-6a75838ad42d",
				"height": 800,
				"width": 600,
				"url": "http://ci.xiaohongshu.com/c31f8a4b-4cae-3d34-8be5-6a75838ad42d?imageView2/2/w/540/format/jpg",
				"original": "http://ci.xiaohongshu.com/c31f8a4b-4cae-3d34-8be5-6a75838ad42d",
				"url_size_large": "http://ci.xiaohongshu.com/c31f8a4b-4cae-3d34-8be5-6a75838ad42d?imageView2/2/w/1080/format/jpg"
			}],
			"is_ads": false
		}, {
			"liked": false,
			"id": "5c6f7fd5000000000e01a25a",
			"title": "",
			"desc": "让李佳琦心脏骤停2s的口红\uD83C\uDF77香奈儿新色116绝美树莓色 ▪️冷白皮 ▪️浅唇 ▪️试色无滤镜 \uD83D\uDC84CHANEL",
			"type": "normal",
			"user": {
				"images": "https://img.xiaohongshu.com/avatar/5ab296e5b46c5d135f3cdda9.jpg@80w_80h_90q_1e_1c_1x.jpg",
				"nickname": "我的猪呢__",
				"red_official_verified": false,
				"red_official_verify_type": 0,
				"userid": "58fb360a50c4b40427a401b7"
			},
			"image_info": {
				"fileid": "7bf6f49b-4261-3b30-a6dc-363a3bec5e86",
				"height": 1280,
				"width": 960,
				"url": "http://ci.xiaohongshu.com/7bf6f49b-4261-3b30-a6dc-363a3bec5e86?imageView2/2/w/540/format/jpg",
				"original": "http://ci.xiaohongshu.com/7bf6f49b-4261-3b30-a6dc-363a3bec5e86",
				"index": 0,
				"url_size_large": "http://ci.xiaohongshu.com/7bf6f49b-4261-3b30-a6dc-363a3bec5e86?imageView2/2/w/1080/format/jpg"
			},
			"liked_count": 7874,
			"tag_info": {},
			"images_list": [{
				"fileid": "7bf6f49b-4261-3b30-a6dc-363a3bec5e86",
				"height": 1280,
				"width": 960,
				"url": "http://ci.xiaohongshu.com/7bf6f49b-4261-3b30-a6dc-363a3bec5e86?imageView2/2/w/540/format/jpg",
				"original": "http://ci.xiaohongshu.com/7bf6f49b-4261-3b30-a6dc-363a3bec5e86",
				"index": 0,
				"url_size_large": "http://ci.xiaohongshu.com/7bf6f49b-4261-3b30-a6dc-363a3bec5e86?imageView2/2/w/1080/format/jpg"
			}, {
				"fileid": "d8e00d70-3018-3cda-b138-e7c969c07f20",
				"height": 1000,
				"width": 750,
				"url": "http://ci.xiaohongshu.com/d8e00d70-3018-3cda-b138-e7c969c07f20?imageView2/2/w/540/format/jpg",
				"original": "http://ci.xiaohongshu.com/d8e00d70-3018-3cda-b138-e7c969c07f20",
				"url_size_large": "http://ci.xiaohongshu.com/d8e00d70-3018-3cda-b138-e7c969c07f20?imageView2/2/w/1080/format/jpg"
			}],
			"is_ads": false
		}, {
			"liked": false,
			"id": "5c91fa81000000000e0240f5",
			"title": "",
			"desc": "YSL黑管416 橘棕烂番茄 日常显白口红试色 阿玛尼405对比 太喜欢416里带的那一点点的棕橘感\uD83C\uDF45！！！ 好好看一",
			"type": "normal",
			"user": {
				"images": "https://img.xiaohongshu.com/avatar/5baf16a8a8b1e20001ea2828.jpg@80w_80h_90q_1e_1c_1x.jpg",
				"nickname": "October_黄梓淇",
				"red_official_verified": false,
				"red_official_verify_type": 0,
				"userid": "562f2f0c82718c772b1ce432"
			},
			"image_info": {
				"fileid": "70d32216-13b4-5337-8449-76f0e0449b05",
				"height": 720,
				"width": 540,
				"url": "http://ci.xiaohongshu.com/70d32216-13b4-5337-8449-76f0e0449b05?imageView2/2/w/540/format/jpg",
				"original": "http://ci.xiaohongshu.com/70d32216-13b4-5337-8449-76f0e0449b05",
				"index": 0,
				"url_size_large": "http://ci.xiaohongshu.com/70d32216-13b4-5337-8449-76f0e0449b05?imageView2/2/w/1080/format/jpg"
			},
			"liked_count": 4011,
			"tag_info": {},
			"images_list": [{
				"fileid": "70d32216-13b4-5337-8449-76f0e0449b05",
				"height": 720,
				"width": 540,
				"url": "http://ci.xiaohongshu.com/70d32216-13b4-5337-8449-76f0e0449b05?imageView2/2/w/540/format/jpg",
				"original": "http://ci.xiaohongshu.com/70d32216-13b4-5337-8449-76f0e0449b05",
				"index": 0,
				"url_size_large": "http://ci.xiaohongshu.com/70d32216-13b4-5337-8449-76f0e0449b05?imageView2/2/w/1080/format/jpg"
			}, {
				"fileid": "514736d5-108a-5e24-8de2-63bbdeac3eb0",
				"height": 720,
				"width": 540,
				"url": "http://ci.xiaohongshu.com/514736d5-108a-5e24-8de2-63bbdeac3eb0?imageView2/2/w/540/format/jpg",
				"original": "http://ci.xiaohongshu.com/514736d5-108a-5e24-8de2-63bbdeac3eb0",
				"url_size_large": "http://ci.xiaohongshu.com/514736d5-108a-5e24-8de2-63bbdeac3eb0?imageView2/2/w/1080/format/jpg"
			}, {
				"fileid": "04e78d88-4614-566c-9923-ff10aa8ecd1d",
				"height": 720,
				"width": 540,
				"url": "http://ci.xiaohongshu.com/04e78d88-4614-566c-9923-ff10aa8ecd1d?imageView2/2/w/540/format/jpg",
				"original": "http://ci.xiaohongshu.com/04e78d88-4614-566c-9923-ff10aa8ecd1d",
				"url_size_large": "http://ci.xiaohongshu.com/04e78d88-4614-566c-9923-ff10aa8ecd1d?imageView2/2/w/1080/format/jpg"
			}, {
				"fileid": "468e79a1-641c-55a0-aacb-6d80caf1485e",
				"height": 720,
				"width": 540,
				"url": "http://ci.xiaohongshu.com/468e79a1-641c-55a0-aacb-6d80caf1485e?imageView2/2/w/540/format/jpg",
				"original": "http://ci.xiaohongshu.com/468e79a1-641c-55a0-aacb-6d80caf1485e",
				"url_size_large": "http://ci.xiaohongshu.com/468e79a1-641c-55a0-aacb-6d80caf1485e?imageView2/2/w/1080/format/jpg"
			}],
			"is_ads": false
		}, {
			"liked": false,
			"id": "5c959b00000000000f0069a8",
			"title": "chanel这支新色 提前内定为19年度最爱口红！",
			"desc": "\uD83D\uDC8B怎么会有这么美的口红啊！我要夸爆它！从颜色到质地都很完美！ \uD83D\uDC8BChanel coco flash 106 \uD83D\uDC8B颜色",
			"type": "normal",
			"user": {
				"images": "https://img.xiaohongshu.com/avatar/5cff4b47f25e1a000132e93f.jpg@80w_80h_90q_1e_1c_1x.jpg",
				"nickname": "-寰-",
				"red_official_verified": false,
				"red_official_verify_type": 0,
				"userid": "54393f6ed6e4a9068205bcd6"
			},
			"image_info": {
				"fileid": "40b0a08d-89d1-584c-a5a3-cf552379250d",
				"height": 1280,
				"width": 1280,
				"url": "http://ci.xiaohongshu.com/40b0a08d-89d1-584c-a5a3-cf552379250d?imageView2/2/w/540/format/jpg",
				"original": "http://ci.xiaohongshu.com/40b0a08d-89d1-584c-a5a3-cf552379250d",
				"index": 0,
				"url_size_large": "http://ci.xiaohongshu.com/40b0a08d-89d1-584c-a5a3-cf552379250d?imageView2/2/w/1080/format/jpg"
			},
			"liked_count": 11350,
			"tag_info": {},
			"images_list": [{
				"fileid": "40b0a08d-89d1-584c-a5a3-cf552379250d",
				"height": 1280,
				"width": 1280,
				"url": "http://ci.xiaohongshu.com/40b0a08d-89d1-584c-a5a3-cf552379250d?imageView2/2/w/540/format/jpg",
				"original": "http://ci.xiaohongshu.com/40b0a08d-89d1-584c-a5a3-cf552379250d",
				"index": 0,
				"url_size_large": "http://ci.xiaohongshu.com/40b0a08d-89d1-584c-a5a3-cf552379250d?imageView2/2/w/1080/format/jpg"
			}, {
				"fileid": "f486fe93-bd39-5163-a8e6-3ca975a083fa",
				"height": 1280,
				"width": 1280,
				"url": "http://ci.xiaohongshu.com/f486fe93-bd39-5163-a8e6-3ca975a083fa?imageView2/2/w/540/format/jpg",
				"original": "http://ci.xiaohongshu.com/f486fe93-bd39-5163-a8e6-3ca975a083fa",
				"url_size_large": "http://ci.xiaohongshu.com/f486fe93-bd39-5163-a8e6-3ca975a083fa?imageView2/2/w/1080/format/jpg"
			}, {
				"fileid": "a5f123f6-8845-5692-bcf3-74328487b7d7",
				"height": 1280,
				"width": 1280,
				"url": "http://ci.xiaohongshu.com/a5f123f6-8845-5692-bcf3-74328487b7d7?imageView2/2/w/540/format/jpg",
				"original": "http://ci.xiaohongshu.com/a5f123f6-8845-5692-bcf3-74328487b7d7",
				"url_size_large": "http://ci.xiaohongshu.com/a5f123f6-8845-5692-bcf3-74328487b7d7?imageView2/2/w/1080/format/jpg"
			}, {
				"fileid": "37fc043c-0fcf-5b4e-b436-b80bb95abe99",
				"height": 1280,
				"width": 1280,
				"url": "http://ci.xiaohongshu.com/37fc043c-0fcf-5b4e-b436-b80bb95abe99?imageView2/2/w/540/format/jpg",
				"original": "http://ci.xiaohongshu.com/37fc043c-0fcf-5b4e-b436-b80bb95abe99",
				"url_size_large": "http://ci.xiaohongshu.com/37fc043c-0fcf-5b4e-b436-b80bb95abe99?imageView2/2/w/1080/format/jpg"
			}, {
				"fileid": "28256339-c2d8-5809-ba65-346c00a83a8a",
				"height": 1280,
				"width": 1280,
				"url": "http://ci.xiaohongshu.com/28256339-c2d8-5809-ba65-346c00a83a8a?imageView2/2/w/540/format/jpg",
				"original": "http://ci.xiaohongshu.com/28256339-c2d8-5809-ba65-346c00a83a8a",
				"url_size_large": "http://ci.xiaohongshu.com/28256339-c2d8-5809-ba65-346c00a83a8a?imageView2/2/w/1080/format/jpg"
			}, {
				"fileid": "2829941c-edc9-5bf7-9637-f3efe78405b5",
				"height": 1280,
				"width": 1280,
				"url": "http://ci.xiaohongshu.com/2829941c-edc9-5bf7-9637-f3efe78405b5?imageView2/2/w/540/format/jpg",
				"original": "http://ci.xiaohongshu.com/2829941c-edc9-5bf7-9637-f3efe78405b5",
				"url_size_large": "http://ci.xiaohongshu.com/2829941c-edc9-5bf7-9637-f3efe78405b5?imageView2/2/w/1080/format/jpg"
			}, {
				"fileid": "a338ad89-0060-5fd1-b55f-2e5319b60a46",
				"height": 1280,
				"width": 1280,
				"url": "http://ci.xiaohongshu.com/a338ad89-0060-5fd1-b55f-2e5319b60a46?imageView2/2/w/540/format/jpg",
				"original": "http://ci.xiaohongshu.com/a338ad89-0060-5fd1-b55f-2e5319b60a46",
				"url_size_large": "http://ci.xiaohongshu.com/a338ad89-0060-5fd1-b55f-2e5319b60a46?imageView2/2/w/1080/format/jpg"
			}, {
				"fileid": "269cacf9-4838-5ced-b025-2ac408ea3e68",
				"height": 1280,
				"width": 1280,
				"url": "http://ci.xiaohongshu.com/269cacf9-4838-5ced-b025-2ac408ea3e68?imageView2/2/w/540/format/jpg",
				"original": "http://ci.xiaohongshu.com/269cacf9-4838-5ced-b025-2ac408ea3e68",
				"url_size_large": "http://ci.xiaohongshu.com/269cacf9-4838-5ced-b025-2ac408ea3e68?imageView2/2/w/1080/format/jpg"
			}, {
				"fileid": "20bdd484-5039-5853-b5b9-f48ad67f28ef",
				"height": 1280,
				"width": 1280,
				"url": "http://ci.xiaohongshu.com/20bdd484-5039-5853-b5b9-f48ad67f28ef?imageView2/2/w/540/format/jpg",
				"original": "http://ci.xiaohongshu.com/20bdd484-5039-5853-b5b9-f48ad67f28ef",
				"url_size_large": "http://ci.xiaohongshu.com/20bdd484-5039-5853-b5b9-f48ad67f28ef?imageView2/2/w/1080/format/jpg"
			}],
			"is_ads": false
		}, {
			"liked": false,
			"id": "5c8cf262000000000d03e8c6",
			"title": "",
			"desc": "我！哭！了！这支浆果色口红也太显白了吧！！我的本命色哇\uD83D\uDC84 - 可能因为看腻了橘色系，我最近一直喜欢玫调的口红，收了好几",
			"type": "normal",
			"user": {
				"images": "https://img.xiaohongshu.com/avatar/5a741b31b46c5d0428ded6c0.jpg@80w_80h_90q_1e_1c_1x.jpg",
				"nickname": "小奶尼-",
				"red_official_verified": false,
				"red_official_verify_type": 0,
				"userid": "59fb089511be102730846fe8"
			},
			"image_info": {
				"fileid": "0212df29-3dff-5c2d-8557-78a47718595a",
				"height": 1278,
				"width": 958,
				"url": "http://ci.xiaohongshu.com/0212df29-3dff-5c2d-8557-78a47718595a?imageView2/2/w/540/format/jpg",
				"original": "http://ci.xiaohongshu.com/0212df29-3dff-5c2d-8557-78a47718595a",
				"index": 0,
				"url_size_large": "http://ci.xiaohongshu.com/0212df29-3dff-5c2d-8557-78a47718595a?imageView2/2/w/1080/format/jpg"
			},
			"liked_count": 11288,
			"tag_info": {},
			"images_list": [{
				"fileid": "0212df29-3dff-5c2d-8557-78a47718595a",
				"height": 1278,
				"width": 958,
				"url": "http://ci.xiaohongshu.com/0212df29-3dff-5c2d-8557-78a47718595a?imageView2/2/w/540/format/jpg",
				"original": "http://ci.xiaohongshu.com/0212df29-3dff-5c2d-8557-78a47718595a",
				"index": 0,
				"url_size_large": "http://ci.xiaohongshu.com/0212df29-3dff-5c2d-8557-78a47718595a?imageView2/2/w/1080/format/jpg"
			}, {
				"fileid": "5ffca19a-59ed-5809-b966-cd28d7dc3ba4",
				"height": 1280,
				"width": 959,
				"url": "http://ci.xiaohongshu.com/5ffca19a-59ed-5809-b966-cd28d7dc3ba4?imageView2/2/w/540/format/jpg",
				"original": "http://ci.xiaohongshu.com/5ffca19a-59ed-5809-b966-cd28d7dc3ba4",
				"url_size_large": "http://ci.xiaohongshu.com/5ffca19a-59ed-5809-b966-cd28d7dc3ba4?imageView2/2/w/1080/format/jpg"
			}, {
				"fileid": "9f827339-d178-53f7-b73c-ba823b2088a0",
				"height": 1280,
				"width": 959,
				"url": "http://ci.xiaohongshu.com/9f827339-d178-53f7-b73c-ba823b2088a0?imageView2/2/w/540/format/jpg",
				"original": "http://ci.xiaohongshu.com/9f827339-d178-53f7-b73c-ba823b2088a0",
				"url_size_large": "http://ci.xiaohongshu.com/9f827339-d178-53f7-b73c-ba823b2088a0?imageView2/2/w/1080/format/jpg"
			}, {
				"fileid": "211ababf-73a6-5efe-a2b1-d2f2a3d32091",
				"height": 1280,
				"width": 960,
				"url": "http://ci.xiaohongshu.com/211ababf-73a6-5efe-a2b1-d2f2a3d32091?imageView2/2/w/540/format/jpg",
				"original": "http://ci.xiaohongshu.com/211ababf-73a6-5efe-a2b1-d2f2a3d32091",
				"url_size_large": "http://ci.xiaohongshu.com/211ababf-73a6-5efe-a2b1-d2f2a3d32091?imageView2/2/w/1080/format/jpg"
			}, {
				"fileid": "344c5c7d-3599-536a-9e20-69fb065929ef",
				"height": 1280,
				"width": 960,
				"url": "http://ci.xiaohongshu.com/344c5c7d-3599-536a-9e20-69fb065929ef?imageView2/2/w/540/format/jpg",
				"original": "http://ci.xiaohongshu.com/344c5c7d-3599-536a-9e20-69fb065929ef",
				"url_size_large": "http://ci.xiaohongshu.com/344c5c7d-3599-536a-9e20-69fb065929ef?imageView2/2/w/1080/format/jpg"
			}],
			"is_ads": false
		}, {
			"liked": false,
			"id": "5ce687eb000000000f03438c",
			"title": "让李佳琦OMG❗️最值得入手的10支大牌口红\uD83D\uDC84",
			"desc": "\uD83D\uDC97分享十支我用过觉得颜色和质地上都很爱的口红，看看你有几支呢？ \uD83D\uDC84DIOR 999 ❤️正红色 \uD83D\uDC49\uD83C\uDFFB人生中必须拥",
			"type": "normal",
			"user": {
				"images": "https://img.xiaohongshu.com/avatar/5ccf9fe412a91b0001703f08.jpg@80w_80h_90q_1e_1c_1x.jpg",
				"nickname": "梨花酱",
				"red_official_verified": false,
				"red_official_verify_type": 0,
				"userid": "54808c28d6e4a9622702cf81"
			},
			"image_info": {
				"fileid": "e1157360-0922-5074-a908-0eeb8cb3f221",
				"height": 960,
				"width": 720,
				"url": "http://ci.xiaohongshu.com/e1157360-0922-5074-a908-0eeb8cb3f221?imageView2/2/w/540/format/jpg",
				"original": "http://ci.xiaohongshu.com/e1157360-0922-5074-a908-0eeb8cb3f221",
				"index": 0,
				"url_size_large": "http://ci.xiaohongshu.com/e1157360-0922-5074-a908-0eeb8cb3f221?imageView2/2/w/1080/format/jpg"
			},
			"liked_count": 4211,
			"tag_info": {},
			"images_list": [{
				"fileid": "e1157360-0922-5074-a908-0eeb8cb3f221",
				"height": 960,
				"width": 720,
				"url": "http://ci.xiaohongshu.com/e1157360-0922-5074-a908-0eeb8cb3f221?imageView2/2/w/540/format/jpg",
				"original": "http://ci.xiaohongshu.com/e1157360-0922-5074-a908-0eeb8cb3f221",
				"index": 0,
				"url_size_large": "http://ci.xiaohongshu.com/e1157360-0922-5074-a908-0eeb8cb3f221?imageView2/2/w/1080/format/jpg"
			}, {
				"fileid": "ac149671-9718-56e8-8060-d88aac9769dc",
				"height": 960,
				"width": 720,
				"url": "http://ci.xiaohongshu.com/ac149671-9718-56e8-8060-d88aac9769dc?imageView2/2/w/540/format/jpg",
				"original": "http://ci.xiaohongshu.com/ac149671-9718-56e8-8060-d88aac9769dc",
				"url_size_large": "http://ci.xiaohongshu.com/ac149671-9718-56e8-8060-d88aac9769dc?imageView2/2/w/1080/format/jpg"
			}, {
				"fileid": "8520cb91-507d-5af2-a697-d692f796ba58",
				"height": 960,
				"width": 720,
				"url": "http://ci.xiaohongshu.com/8520cb91-507d-5af2-a697-d692f796ba58?imageView2/2/w/540/format/jpg",
				"original": "http://ci.xiaohongshu.com/8520cb91-507d-5af2-a697-d692f796ba58",
				"url_size_large": "http://ci.xiaohongshu.com/8520cb91-507d-5af2-a697-d692f796ba58?imageView2/2/w/1080/format/jpg"
			}, {
				"fileid": "3aa1a006-64f4-5ebe-9b6a-5eeaf4250db4",
				"height": 960,
				"width": 720,
				"url": "http://ci.xiaohongshu.com/3aa1a006-64f4-5ebe-9b6a-5eeaf4250db4?imageView2/2/w/540/format/jpg",
				"original": "http://ci.xiaohongshu.com/3aa1a006-64f4-5ebe-9b6a-5eeaf4250db4",
				"url_size_large": "http://ci.xiaohongshu.com/3aa1a006-64f4-5ebe-9b6a-5eeaf4250db4?imageView2/2/w/1080/format/jpg"
			}, {
				"fileid": "ad660068-4f1e-5b5e-b629-44172a3e34fc",
				"height": 960,
				"width": 720,
				"url": "http://ci.xiaohongshu.com/ad660068-4f1e-5b5e-b629-44172a3e34fc?imageView2/2/w/540/format/jpg",
				"original": "http://ci.xiaohongshu.com/ad660068-4f1e-5b5e-b629-44172a3e34fc",
				"url_size_large": "http://ci.xiaohongshu.com/ad660068-4f1e-5b5e-b629-44172a3e34fc?imageView2/2/w/1080/format/jpg"
			}, {
				"fileid": "adb717d8-b253-5afa-a5a4-2410d6a9315f",
				"height": 960,
				"width": 720,
				"url": "http://ci.xiaohongshu.com/adb717d8-b253-5afa-a5a4-2410d6a9315f?imageView2/2/w/540/format/jpg",
				"original": "http://ci.xiaohongshu.com/adb717d8-b253-5afa-a5a4-2410d6a9315f",
				"url_size_large": "http://ci.xiaohongshu.com/adb717d8-b253-5afa-a5a4-2410d6a9315f?imageView2/2/w/1080/format/jpg"
			}],
			"is_ads": false
		}, {
			"title": "",
			"desc": "",
			"is_ads": true,
			"ads_info": {
				"ads_id": "115199",
				"track_id": "adscpcg_477ba8de-8c47-11e9-bce5-52540018ffb6@c83568158a134f08a3118c37dfaa03b5",
				"show_tag": true,
				"is_banner": false,
				"banner_info": {
					"desc": ""
				},
				"trackPos": 1,
				"is_goods": true,
				"goods_info": {
					"title": "中国·新品「小金钻」",
					"desc": "完美日记perfect diary 星动臻色金钻唇膏 A02",
					"id": "5ca175f9065d1d6742f6511c",
					"link": "xhsdiscover://webview/www.xiaohongshu.com/goods/5ca175f9065d1d6742f6511c?isRN=true&rnName=fantasy-goods-detail-rn&rnPath=goods/5ca175f9065d1d6742f6511c",
					"tags": [],
					"image_info": {
						"url": "https://qimg.xiaohongshu.com/995fde80-948c-11e9-b8b0-1dfad475270d-7zlvwd?imageView2/1/w/320/h/320/q/90.jpg",
						"height": 320,
						"width": 320
					},
					"item_price": [{
						"type": "sale_price",
						"price": 79.9,
						"index": 1
					}, {
						"type": "origin_price",
						"price": 169.0,
						"index": 3
					}],
					"vendor_icon": "http://img.xiaohongshu.com/seller/b88372dc9ab28d3a6d232674a786e7a2"
				}
			}
		}, {
			"liked": false,
			"id": "5cfe16130000000028032462",
			"title": "MAC新色531 口红千千万 新色最好看❗️",
			"desc": "哈哈哈哈哈 剁手女孩们 请跟着我一起喊出口号 世上口红千千万 只有新色最好看～ 今日份试色\uD83D\uDC84mac新色531 good",
			"type": "normal",
			"user": {
				"images": "https://img.xiaohongshu.com/avatar/5b79583825ebbe0001d5eab7.jpg@80w_80h_90q_1e_1c_1x.jpg",
				"nickname": "SiHueee",
				"red_official_verified": false,
				"red_official_verify_type": 0,
				"userid": "5783654ba9b2ed2c1339acd6"
			},
			"image_info": {
				"fileid": "2aff3f17-c18c-3243-b203-dc753882730d",
				"height": 1280,
				"width": 1280,
				"url": "http://ci.xiaohongshu.com/2aff3f17-c18c-3243-b203-dc753882730d?imageView2/2/w/540/format/jpg",
				"original": "http://ci.xiaohongshu.com/2aff3f17-c18c-3243-b203-dc753882730d",
				"index": 0,
				"url_size_large": "http://ci.xiaohongshu.com/2aff3f17-c18c-3243-b203-dc753882730d?imageView2/2/w/1080/format/jpg"
			},
			"liked_count": 828,
			"tag_info": {},
			"images_list": [{
				"fileid": "2aff3f17-c18c-3243-b203-dc753882730d",
				"height": 1280,
				"width": 1280,
				"url": "http://ci.xiaohongshu.com/2aff3f17-c18c-3243-b203-dc753882730d?imageView2/2/w/540/format/jpg",
				"original": "http://ci.xiaohongshu.com/2aff3f17-c18c-3243-b203-dc753882730d",
				"index": 0,
				"url_size_large": "http://ci.xiaohongshu.com/2aff3f17-c18c-3243-b203-dc753882730d?imageView2/2/w/1080/format/jpg"
			}, {
				"fileid": "4881d040-69c9-3f10-96b8-7d429346f489",
				"height": 1280,
				"width": 1280,
				"url": "http://ci.xiaohongshu.com/4881d040-69c9-3f10-96b8-7d429346f489?imageView2/2/w/540/format/jpg",
				"original": "http://ci.xiaohongshu.com/4881d040-69c9-3f10-96b8-7d429346f489",
				"url_size_large": "http://ci.xiaohongshu.com/4881d040-69c9-3f10-96b8-7d429346f489?imageView2/2/w/1080/format/jpg"
			}, {
				"fileid": "6e1c86ae-7b75-3b2a-8332-9a100b23935f",
				"height": 1280,
				"width": 1280,
				"url": "http://ci.xiaohongshu.com/6e1c86ae-7b75-3b2a-8332-9a100b23935f?imageView2/2/w/540/format/jpg",
				"original": "http://ci.xiaohongshu.com/6e1c86ae-7b75-3b2a-8332-9a100b23935f",
				"url_size_large": "http://ci.xiaohongshu.com/6e1c86ae-7b75-3b2a-8332-9a100b23935f?imageView2/2/w/1080/format/jpg"
			}, {
				"fileid": "e01dcacc-961a-392f-a671-26b454433675",
				"height": 1280,
				"width": 1280,
				"url": "http://ci.xiaohongshu.com/e01dcacc-961a-392f-a671-26b454433675?imageView2/2/w/540/format/jpg",
				"original": "http://ci.xiaohongshu.com/e01dcacc-961a-392f-a671-26b454433675",
				"url_size_large": "http://ci.xiaohongshu.com/e01dcacc-961a-392f-a671-26b454433675?imageView2/2/w/1080/format/jpg"
			}, {
				"fileid": "dd6d28f3-f3ef-3c8a-be1f-ad2bd1f9fee3",
				"height": 1280,
				"width": 1280,
				"url": "http://ci.xiaohongshu.com/dd6d28f3-f3ef-3c8a-be1f-ad2bd1f9fee3?imageView2/2/w/540/format/jpg",
				"original": "http://ci.xiaohongshu.com/dd6d28f3-f3ef-3c8a-be1f-ad2bd1f9fee3",
				"url_size_large": "http://ci.xiaohongshu.com/dd6d28f3-f3ef-3c8a-be1f-ad2bd1f9fee3?imageView2/2/w/1080/format/jpg"
			}, {
				"fileid": "0a557df3-6703-3adc-985f-6c49da46b86f",
				"height": 1280,
				"width": 1280,
				"url": "http://ci.xiaohongshu.com/0a557df3-6703-3adc-985f-6c49da46b86f?imageView2/2/w/540/format/jpg",
				"original": "http://ci.xiaohongshu.com/0a557df3-6703-3adc-985f-6c49da46b86f",
				"url_size_large": "http://ci.xiaohongshu.com/0a557df3-6703-3adc-985f-6c49da46b86f?imageView2/2/w/1080/format/jpg"
			}, {
				"fileid": "995370a6-df84-3a3d-962c-32e266e36717",
				"height": 1280,
				"width": 1280,
				"url": "http://ci.xiaohongshu.com/995370a6-df84-3a3d-962c-32e266e36717?imageView2/2/w/540/format/jpg",
				"original": "http://ci.xiaohongshu.com/995370a6-df84-3a3d-962c-32e266e36717",
				"url_size_large": "http://ci.xiaohongshu.com/995370a6-df84-3a3d-962c-32e266e36717?imageView2/2/w/1080/format/jpg"
			}],
			"is_ads": false
		}, {
			"liked": false,
			"id": "5ce8ebf9000000000e03c096",
			"title": "MAC又来一只抢钱口红...好温柔噢！！",
			"desc": "这个我看过很多博主发了，但是我问过香港代购，还没上，但是据说快了，目前好像只有海外才有，所以，喜欢的，可以找代购问问，或",
			"type": "normal",
			"user": {
				"images": "https://img.xiaohongshu.com/avatar/5c7886ddac05f80001812066.jpg@80w_80h_90q_1e_1c_1x.jpg",
				"nickname": "lexiii_照骗",
				"red_official_verified": false,
				"red_official_verify_type": 0,
				"userid": "57bd2cbc5e87e77b8a7e3049"
			},
			"image_info": {
				"fileid": "0e2ddb58-f199-565b-acbb-91b24b3abe91",
				"height": 1280,
				"width": 1280,
				"url": "http://ci.xiaohongshu.com/0e2ddb58-f199-565b-acbb-91b24b3abe91?imageView2/2/w/540/format/jpg",
				"original": "http://ci.xiaohongshu.com/0e2ddb58-f199-565b-acbb-91b24b3abe91",
				"index": 0,
				"url_size_large": "http://ci.xiaohongshu.com/0e2ddb58-f199-565b-acbb-91b24b3abe91?imageView2/2/w/1080/format/jpg"
			},
			"liked_count": 3133,
			"tag_info": {},
			"images_list": [{
				"fileid": "0e2ddb58-f199-565b-acbb-91b24b3abe91",
				"height": 1280,
				"width": 1280,
				"url": "http://ci.xiaohongshu.com/0e2ddb58-f199-565b-acbb-91b24b3abe91?imageView2/2/w/540/format/jpg",
				"original": "http://ci.xiaohongshu.com/0e2ddb58-f199-565b-acbb-91b24b3abe91",
				"index": 0,
				"url_size_large": "http://ci.xiaohongshu.com/0e2ddb58-f199-565b-acbb-91b24b3abe91?imageView2/2/w/1080/format/jpg"
			}, {
				"fileid": "2a7e2ea5-e018-57b9-b692-ed96e285610d",
				"height": 1280,
				"width": 1280,
				"url": "http://ci.xiaohongshu.com/2a7e2ea5-e018-57b9-b692-ed96e285610d?imageView2/2/w/540/format/jpg",
				"original": "http://ci.xiaohongshu.com/2a7e2ea5-e018-57b9-b692-ed96e285610d",
				"url_size_large": "http://ci.xiaohongshu.com/2a7e2ea5-e018-57b9-b692-ed96e285610d?imageView2/2/w/1080/format/jpg"
			}, {
				"fileid": "5b2ac7be-e08c-576b-98f3-d44310ab61da",
				"height": 1016,
				"width": 1016,
				"url": "http://ci.xiaohongshu.com/5b2ac7be-e08c-576b-98f3-d44310ab61da?imageView2/2/w/540/format/jpg",
				"original": "http://ci.xiaohongshu.com/5b2ac7be-e08c-576b-98f3-d44310ab61da",
				"url_size_large": "http://ci.xiaohongshu.com/5b2ac7be-e08c-576b-98f3-d44310ab61da?imageView2/2/w/1080/format/jpg"
			}, {
				"fileid": "5143ce73-b93d-5687-b371-b2e68ba69919",
				"height": 1280,
				"width": 1280,
				"url": "http://ci.xiaohongshu.com/5143ce73-b93d-5687-b371-b2e68ba69919?imageView2/2/w/540/format/jpg",
				"original": "http://ci.xiaohongshu.com/5143ce73-b93d-5687-b371-b2e68ba69919",
				"url_size_large": "http://ci.xiaohongshu.com/5143ce73-b93d-5687-b371-b2e68ba69919?imageView2/2/w/1080/format/jpg"
			}, {
				"fileid": "95311197-83e2-530c-8eac-11ae06227312",
				"height": 1280,
				"width": 1280,
				"url": "http://ci.xiaohongshu.com/95311197-83e2-530c-8eac-11ae06227312?imageView2/2/w/540/format/jpg",
				"original": "http://ci.xiaohongshu.com/95311197-83e2-530c-8eac-11ae06227312",
				"url_size_large": "http://ci.xiaohongshu.com/95311197-83e2-530c-8eac-11ae06227312?imageView2/2/w/1080/format/jpg"
			}],
			"is_ads": false
		}, {
			"liked": false,
			"id": "5d0ae42e000000002603aa5f",
			"title": "",
			"desc": "忘掉5毛钱的口红壳子 植村秀是黄皮女孩的本命 [斜眼R] 亚洲黄皮女孩本命口红，是植村秀了~她好用的不止眉笔，口红也是超",
			"type": "normal",
			"user": {
				"images": "https://img.xiaohongshu.com/avatar/5b960d9892f8a0000156cf0d.jpg@80w_80h_90q_1e_1c_1x.jpg",
				"nickname": "伪文艺少女疯疯",
				"red_official_verified": false,
				"red_official_verify_type": 0,
				"userid": "5b7698a286002d000144e730"
			},
			"image_info": {
				"fileid": "c2209b44-1d58-36d5-a112-f6c3f0428478",
				"height": 1280,
				"width": 959,
				"url": "http://ci.xiaohongshu.com/c2209b44-1d58-36d5-a112-f6c3f0428478?imageView2/2/w/540/format/jpg",
				"original": "http://ci.xiaohongshu.com/c2209b44-1d58-36d5-a112-f6c3f0428478",
				"index": 0,
				"url_size_large": "http://ci.xiaohongshu.com/c2209b44-1d58-36d5-a112-f6c3f0428478?imageView2/2/w/1080/format/jpg"
			},
			"liked_count": 696,
			"tag_info": {},
			"images_list": [{
				"fileid": "c2209b44-1d58-36d5-a112-f6c3f0428478",
				"height": 1280,
				"width": 959,
				"url": "http://ci.xiaohongshu.com/c2209b44-1d58-36d5-a112-f6c3f0428478?imageView2/2/w/540/format/jpg",
				"original": "http://ci.xiaohongshu.com/c2209b44-1d58-36d5-a112-f6c3f0428478",
				"index": 0,
				"url_size_large": "http://ci.xiaohongshu.com/c2209b44-1d58-36d5-a112-f6c3f0428478?imageView2/2/w/1080/format/jpg"
			}, {
				"fileid": "98260b77-7570-304f-9d5d-9e520f70896d",
				"height": 1280,
				"width": 959,
				"url": "http://ci.xiaohongshu.com/98260b77-7570-304f-9d5d-9e520f70896d?imageView2/2/w/540/format/jpg",
				"original": "http://ci.xiaohongshu.com/98260b77-7570-304f-9d5d-9e520f70896d",
				"url_size_large": "http://ci.xiaohongshu.com/98260b77-7570-304f-9d5d-9e520f70896d?imageView2/2/w/1080/format/jpg"
			}, {
				"fileid": "a6877fe5-3008-3f62-abc5-1753a5619644",
				"height": 1280,
				"width": 959,
				"url": "http://ci.xiaohongshu.com/a6877fe5-3008-3f62-abc5-1753a5619644?imageView2/2/w/540/format/jpg",
				"original": "http://ci.xiaohongshu.com/a6877fe5-3008-3f62-abc5-1753a5619644",
				"url_size_large": "http://ci.xiaohongshu.com/a6877fe5-3008-3f62-abc5-1753a5619644?imageView2/2/w/1080/format/jpg"
			}, {
				"fileid": "144a1a2e-433d-3035-a508-7812e34ec5eb",
				"height": 1280,
				"width": 959,
				"url": "http://ci.xiaohongshu.com/144a1a2e-433d-3035-a508-7812e34ec5eb?imageView2/2/w/540/format/jpg",
				"original": "http://ci.xiaohongshu.com/144a1a2e-433d-3035-a508-7812e34ec5eb",
				"url_size_large": "http://ci.xiaohongshu.com/144a1a2e-433d-3035-a508-7812e34ec5eb?imageView2/2/w/1080/format/jpg"
			}],
			"is_ads": false
		}, {
			"liked": false,
			"id": "5c209ed7000000000a0256ca",
			"title": "黄皮素颜口红推荐",
			"desc": "\uD83D\uDC67黄皮素颜口红推荐\uD83D\uDC67 \uD83D\uDC67黄皮（算比较黑）深唇， \uD83D\uDC67因为一直有人问，素颜有什么口红推荐，所以就拿自己身边有的口红出",
			"type": "video",
			"user": {
				"images": "https://img.xiaohongshu.com/avatar/5cd778a4bf22ae0001011d5c.jpg@80w_80h_90q_1e_1c_1x.jpg",
				"nickname": "中年少女危机重重",
				"red_official_verified": false,
				"red_official_verify_type": 0,
				"userid": "5ad9337611be105c406bf4a7"
			},
			"video_info": {
				"id": "5c209ed7abb0910001047c37",
				"height": 1280,
				"width": 720,
				"url": "http://v.xiaohongshu.com/65fc582bd713704343395908abaa8eb638726e9b?sign=c0147c27bc3a1d0b8afd68071484026f&t=5d10f380",
				"gif_url": "http://sg.xiaohongshu.com/lrvxOeRo-YBVksIaxNCR_lAVW_jJ_gif_w320?imageView2/0/format/webp",
				"preload_size": 1048576,
				"played_count": 1837945
			},
			"image_info": {
				"fileid": "019209de-719a-5288-bcd2-9cf5bfb4b05e",
				"height": 1280,
				"width": 720,
				"url": "http://ci.xiaohongshu.com/019209de-719a-5288-bcd2-9cf5bfb4b05e?imageView2/2/w/540/format/jpg",
				"original": "http://ci.xiaohongshu.com/019209de-719a-5288-bcd2-9cf5bfb4b05e",
				"index": 0,
				"url_size_large": "http://ci.xiaohongshu.com/019209de-719a-5288-bcd2-9cf5bfb4b05e?imageView2/2/w/1080/format/jpg"
			},
			"liked_count": 12790,
			"tag_info": {},
			"images_list": [{
				"fileid": "019209de-719a-5288-bcd2-9cf5bfb4b05e",
				"height": 1280,
				"width": 720,
				"url": "http://ci.xiaohongshu.com/019209de-719a-5288-bcd2-9cf5bfb4b05e?imageView2/2/w/540/format/jpg",
				"original": "http://ci.xiaohongshu.com/019209de-719a-5288-bcd2-9cf5bfb4b05e",
				"index": 0,
				"url_size_large": "http://ci.xiaohongshu.com/019209de-719a-5288-bcd2-9cf5bfb4b05e?imageView2/2/w/1080/format/jpg"
			}],
			"is_ads": false
		}, {
			"liked": false,
			"id": "5c2f3d620000000008032fd4",
			"title": "",
			"desc": "元气女孩必备口红，每次涂都被追着问色号！ TF的05色号，是我的本命了，每次我涂这只就会有人问是什么色号，所以强烈推荐给",
			"type": "video",
			"user": {
				"images": "https://img.xiaohongshu.com/avatar/56ef751daed75817cf5981dd.jpg@80w_80h_90q_1e_1c_1x.jpg",
				"nickname": "祝绪丹Bambi",
				"red_official_verified": true,
				"red_official_verify_type": 1,
				"userid": "56ef751daed75817cf5981dd"
			},
			"video_info": {
				"id": "5c2f3d6265171a0001daef2e",
				"height": 1280,
				"width": 720,
				"url": "http://v.xiaohongshu.com/f687f9bac9170858600257c8c9cdce5612914e17?sign=fa2c3d8ffe85f7f729f467122319c22e&t=5d10f380",
				"gif_url": "http://sg.xiaohongshu.com/ltpNb9Tx7BdGvK35NYhQeBEQiYCn_gif_w320?imageView2/0/format/webp",
				"preload_size": 1048576,
				"played_count": 6183857
			},
			"image_info": {
				"fileid": "a1cf16d7-b438-30ef-8622-44d56401f5e4",
				"height": 1280,
				"width": 720,
				"url": "http://ci.xiaohongshu.com/a1cf16d7-b438-30ef-8622-44d56401f5e4?imageView2/2/w/540/format/jpg",
				"original": "http://ci.xiaohongshu.com/a1cf16d7-b438-30ef-8622-44d56401f5e4",
				"index": 0,
				"url_size_large": "http://ci.xiaohongshu.com/a1cf16d7-b438-30ef-8622-44d56401f5e4?imageView2/2/w/1080/format/jpg"
			},
			"liked_count": 79920,
			"tag_info": {},
			"images_list": [{
				"fileid": "a1cf16d7-b438-30ef-8622-44d56401f5e4",
				"height": 1280,
				"width": 720,
				"url": "http://ci.xiaohongshu.com/a1cf16d7-b438-30ef-8622-44d56401f5e4?imageView2/2/w/540/format/jpg",
				"original": "http://ci.xiaohongshu.com/a1cf16d7-b438-30ef-8622-44d56401f5e4",
				"index": 0,
				"url_size_large": "http://ci.xiaohongshu.com/a1cf16d7-b438-30ef-8622-44d56401f5e4?imageView2/2/w/1080/format/jpg"
			}],
			"is_ads": false
		}, {
			"liked": false,
			"id": "5cef2e9800000000060366e7",
			"title": "大牌口红热门色号推荐清单\uD83D\uDC84下半辈子不用愁",
			"desc": "七大品牌热门色号的口红清单都在这里啦！！\uD83D\uDC95 以后要买礼物给女朋友 朋友 或者自己 都不用愁不知道买什么了！❤️ \uD83D\uDC34下",
			"type": "normal",
			"user": {
				"images": "https://img.xiaohongshu.com/avatar/5ce7c8c56c843d0001c792d5.jpg@80w_80h_90q_1e_1c_1x.jpg",
				"nickname": "妈我瘦了",
				"red_official_verified": false,
				"red_official_verify_type": 0,
				"userid": "5cdd2824000000001201e7ce"
			},
			"image_info": {
				"fileid": "f24ddec1-18b1-3106-b85d-5362106212d6",
				"height": 960,
				"width": 720,
				"url": "http://ci.xiaohongshu.com/f24ddec1-18b1-3106-b85d-5362106212d6?imageView2/2/w/540/format/jpg",
				"original": "http://ci.xiaohongshu.com/f24ddec1-18b1-3106-b85d-5362106212d6",
				"index": 0,
				"url_size_large": "http://ci.xiaohongshu.com/f24ddec1-18b1-3106-b85d-5362106212d6?imageView2/2/w/1080/format/jpg"
			},
			"liked_count": 8785,
			"tag_info": {},
			"images_list": [{
				"fileid": "f24ddec1-18b1-3106-b85d-5362106212d6",
				"height": 960,
				"width": 720,
				"url": "http://ci.xiaohongshu.com/f24ddec1-18b1-3106-b85d-5362106212d6?imageView2/2/w/540/format/jpg",
				"original": "http://ci.xiaohongshu.com/f24ddec1-18b1-3106-b85d-5362106212d6",
				"index": 0,
				"url_size_large": "http://ci.xiaohongshu.com/f24ddec1-18b1-3106-b85d-5362106212d6?imageView2/2/w/1080/format/jpg"
			}, {
				"fileid": "a7bd5673-d9eb-5b8a-83e0-4348668ad8f0",
				"height": 1280,
				"width": 960,
				"url": "http://ci.xiaohongshu.com/a7bd5673-d9eb-5b8a-83e0-4348668ad8f0?imageView2/2/w/540/format/jpg",
				"original": "http://ci.xiaohongshu.com/a7bd5673-d9eb-5b8a-83e0-4348668ad8f0",
				"url_size_large": "http://ci.xiaohongshu.com/a7bd5673-d9eb-5b8a-83e0-4348668ad8f0?imageView2/2/w/1080/format/jpg"
			}, {
				"fileid": "3cc31ac5-7789-5445-bc82-590cd1c9a6a1",
				"height": 1280,
				"width": 960,
				"url": "http://ci.xiaohongshu.com/3cc31ac5-7789-5445-bc82-590cd1c9a6a1?imageView2/2/w/540/format/jpg",
				"original": "http://ci.xiaohongshu.com/3cc31ac5-7789-5445-bc82-590cd1c9a6a1",
				"url_size_large": "http://ci.xiaohongshu.com/3cc31ac5-7789-5445-bc82-590cd1c9a6a1?imageView2/2/w/1080/format/jpg"
			}, {
				"fileid": "76231aa6-28ce-5fc4-b077-bb1f242071cf",
				"height": 1280,
				"width": 960,
				"url": "http://ci.xiaohongshu.com/76231aa6-28ce-5fc4-b077-bb1f242071cf?imageView2/2/w/540/format/jpg",
				"original": "http://ci.xiaohongshu.com/76231aa6-28ce-5fc4-b077-bb1f242071cf",
				"url_size_large": "http://ci.xiaohongshu.com/76231aa6-28ce-5fc4-b077-bb1f242071cf?imageView2/2/w/1080/format/jpg"
			}, {
				"fileid": "0fb6e607-fa81-5ef0-bf0f-033fb15332ea",
				"height": 1280,
				"width": 960,
				"url": "http://ci.xiaohongshu.com/0fb6e607-fa81-5ef0-bf0f-033fb15332ea?imageView2/2/w/540/format/jpg",
				"original": "http://ci.xiaohongshu.com/0fb6e607-fa81-5ef0-bf0f-033fb15332ea",
				"url_size_large": "http://ci.xiaohongshu.com/0fb6e607-fa81-5ef0-bf0f-033fb15332ea?imageView2/2/w/1080/format/jpg"
			}, {
				"fileid": "68f132fe-d793-5204-bd6e-97f1ef23e13c",
				"height": 1280,
				"width": 960,
				"url": "http://ci.xiaohongshu.com/68f132fe-d793-5204-bd6e-97f1ef23e13c?imageView2/2/w/540/format/jpg",
				"original": "http://ci.xiaohongshu.com/68f132fe-d793-5204-bd6e-97f1ef23e13c",
				"url_size_large": "http://ci.xiaohongshu.com/68f132fe-d793-5204-bd6e-97f1ef23e13c?imageView2/2/w/1080/format/jpg"
			}, {
				"fileid": "96e8915d-4722-5da7-976d-9a662e907a9f",
				"height": 1280,
				"width": 960,
				"url": "http://ci.xiaohongshu.com/96e8915d-4722-5da7-976d-9a662e907a9f?imageView2/2/w/540/format/jpg",
				"original": "http://ci.xiaohongshu.com/96e8915d-4722-5da7-976d-9a662e907a9f",
				"url_size_large": "http://ci.xiaohongshu.com/96e8915d-4722-5da7-976d-9a662e907a9f?imageView2/2/w/1080/format/jpg"
			}, {
				"fileid": "5a6fa0c8-57c5-517d-8647-1e5a8e6089c0",
				"height": 1280,
				"width": 960,
				"url": "http://ci.xiaohongshu.com/5a6fa0c8-57c5-517d-8647-1e5a8e6089c0?imageView2/2/w/540/format/jpg",
				"original": "http://ci.xiaohongshu.com/5a6fa0c8-57c5-517d-8647-1e5a8e6089c0",
				"url_size_large": "http://ci.xiaohongshu.com/5a6fa0c8-57c5-517d-8647-1e5a8e6089c0?imageView2/2/w/1080/format/jpg"
			}],
			"is_ads": false
		}, {
			"liked": false,
			"id": "5d08b656000000002700ca9d",
			"title": "学生党必备平价口红\uD83D\uDC84黄皮亲妈❗❗巨显白",
			"desc": "✨本人黄一白 这些口红都是平日上学自用的平价口红 百分百无滤镜，下午自然光下拍摄 各位宝宝们一起快乐种\uD83C\uDF43草吧 1⃣co",
			"type": "normal",
			"user": {
				"images": "https://img.xiaohongshu.com/avatar/5b882d052f39bc00015a3546.jpg@80w_80h_90q_1e_1c_1x.jpg",
				"nickname": "你好可爱",
				"red_official_verified": false,
				"red_official_verify_type": 0,
				"userid": "5b882d052f39bc00015a3546"
			},
			"image_info": {
				"fileid": "168823fe-a99e-336b-a9b7-80392aa3042d",
				"height": 1280,
				"width": 960,
				"url": "http://ci.xiaohongshu.com/168823fe-a99e-336b-a9b7-80392aa3042d?imageView2/2/w/540/format/jpg",
				"original": "http://ci.xiaohongshu.com/168823fe-a99e-336b-a9b7-80392aa3042d",
				"index": 0,
				"url_size_large": "http://ci.xiaohongshu.com/168823fe-a99e-336b-a9b7-80392aa3042d?imageView2/2/w/1080/format/jpg"
			},
			"liked_count": 3198,
			"tag_info": {},
			"images_list": [{
				"fileid": "168823fe-a99e-336b-a9b7-80392aa3042d",
				"height": 1280,
				"width": 960,
				"url": "http://ci.xiaohongshu.com/168823fe-a99e-336b-a9b7-80392aa3042d?imageView2/2/w/540/format/jpg",
				"original": "http://ci.xiaohongshu.com/168823fe-a99e-336b-a9b7-80392aa3042d",
				"index": 0,
				"url_size_large": "http://ci.xiaohongshu.com/168823fe-a99e-336b-a9b7-80392aa3042d?imageView2/2/w/1080/format/jpg"
			}, {
				"fileid": "d1df8e9b-cd15-3d56-8707-6c52606e282b",
				"height": 1280,
				"width": 960,
				"url": "http://ci.xiaohongshu.com/d1df8e9b-cd15-3d56-8707-6c52606e282b?imageView2/2/w/540/format/jpg",
				"original": "http://ci.xiaohongshu.com/d1df8e9b-cd15-3d56-8707-6c52606e282b",
				"url_size_large": "http://ci.xiaohongshu.com/d1df8e9b-cd15-3d56-8707-6c52606e282b?imageView2/2/w/1080/format/jpg"
			}, {
				"fileid": "50c97eec-7f5e-33cc-b1f9-c6203cea0939",
				"height": 1280,
				"width": 960,
				"url": "http://ci.xiaohongshu.com/50c97eec-7f5e-33cc-b1f9-c6203cea0939?imageView2/2/w/540/format/jpg",
				"original": "http://ci.xiaohongshu.com/50c97eec-7f5e-33cc-b1f9-c6203cea0939",
				"url_size_large": "http://ci.xiaohongshu.com/50c97eec-7f5e-33cc-b1f9-c6203cea0939?imageView2/2/w/1080/format/jpg"
			}, {
				"fileid": "990563df-6d4e-3263-bdea-6b202d636b60",
				"height": 1280,
				"width": 960,
				"url": "http://ci.xiaohongshu.com/990563df-6d4e-3263-bdea-6b202d636b60?imageView2/2/w/540/format/jpg",
				"original": "http://ci.xiaohongshu.com/990563df-6d4e-3263-bdea-6b202d636b60",
				"url_size_large": "http://ci.xiaohongshu.com/990563df-6d4e-3263-bdea-6b202d636b60?imageView2/2/w/1080/format/jpg"
			}, {
				"fileid": "6450f073-269e-3074-a7c7-f9684ed1bba6",
				"height": 1280,
				"width": 960,
				"url": "http://ci.xiaohongshu.com/6450f073-269e-3074-a7c7-f9684ed1bba6?imageView2/2/w/540/format/jpg",
				"original": "http://ci.xiaohongshu.com/6450f073-269e-3074-a7c7-f9684ed1bba6",
				"url_size_large": "http://ci.xiaohongshu.com/6450f073-269e-3074-a7c7-f9684ed1bba6?imageView2/2/w/1080/format/jpg"
			}, {
				"fileid": "a7b58b8e-d7fe-3f76-be44-01abbd131545",
				"height": 1280,
				"width": 960,
				"url": "http://ci.xiaohongshu.com/a7b58b8e-d7fe-3f76-be44-01abbd131545?imageView2/2/w/540/format/jpg",
				"original": "http://ci.xiaohongshu.com/a7b58b8e-d7fe-3f76-be44-01abbd131545",
				"url_size_large": "http://ci.xiaohongshu.com/a7b58b8e-d7fe-3f76-be44-01abbd131545?imageView2/2/w/1080/format/jpg"
			}, {
				"fileid": "eec2bf5b-8a4d-3fb6-bb1c-91de5b715ec3",
				"height": 1280,
				"width": 960,
				"url": "http://ci.xiaohongshu.com/eec2bf5b-8a4d-3fb6-bb1c-91de5b715ec3?imageView2/2/w/540/format/jpg",
				"original": "http://ci.xiaohongshu.com/eec2bf5b-8a4d-3fb6-bb1c-91de5b715ec3",
				"url_size_large": "http://ci.xiaohongshu.com/eec2bf5b-8a4d-3fb6-bb1c-91de5b715ec3?imageView2/2/w/1080/format/jpg"
			}, {
				"fileid": "2dbed833-7e12-375f-85b4-a41f3a0413c7",
				"height": 1280,
				"width": 960,
				"url": "http://ci.xiaohongshu.com/2dbed833-7e12-375f-85b4-a41f3a0413c7?imageView2/2/w/540/format/jpg",
				"original": "http://ci.xiaohongshu.com/2dbed833-7e12-375f-85b4-a41f3a0413c7",
				"url_size_large": "http://ci.xiaohongshu.com/2dbed833-7e12-375f-85b4-a41f3a0413c7?imageView2/2/w/1080/format/jpg"
			}, {
				"fileid": "30df0219-7433-3bba-9ab4-a46269126e9a",
				"height": 1280,
				"width": 960,
				"url": "http://ci.xiaohongshu.com/30df0219-7433-3bba-9ab4-a46269126e9a?imageView2/2/w/540/format/jpg",
				"original": "http://ci.xiaohongshu.com/30df0219-7433-3bba-9ab4-a46269126e9a",
				"url_size_large": "http://ci.xiaohongshu.com/30df0219-7433-3bba-9ab4-a46269126e9a?imageView2/2/w/1080/format/jpg"
			}],
			"is_ads": false
		}, {
			"liked": false,
			"id": "5cf4fc7d0000000028039d4b",
			"title": "想要回购无数支的口红！颜色质感都太好了！",
			"desc": "最近香奈儿这款口红风很大啊！我也抵不住诱惑了[色色R]由于106和70都太火了，都没有现货，我就先买了这支90号。结果没",
			"type": "normal",
			"user": {
				"images": "https://img.xiaohongshu.com/avatar/5b58835fb46c5d49c475eefb.jpg@80w_80h_90q_1e_1c_1x.jpg",
				"nickname": "阿楠爱次肉呀",
				"red_official_verified": false,
				"red_official_verify_type": 0,
				"userid": "5a8048054eacab72cdb9e719"
			},
			"image_info": {
				"fileid": "d524986e-7740-3295-8152-6b32a12c5fa4",
				"height": 1280,
				"width": 1280,
				"url": "http://ci.xiaohongshu.com/d524986e-7740-3295-8152-6b32a12c5fa4?imageView2/2/w/540/format/jpg",
				"original": "http://ci.xiaohongshu.com/d524986e-7740-3295-8152-6b32a12c5fa4",
				"index": 0,
				"url_size_large": "http://ci.xiaohongshu.com/d524986e-7740-3295-8152-6b32a12c5fa4?imageView2/2/w/1080/format/jpg"
			},
			"liked_count": 904,
			"tag_info": {},
			"images_list": [{
				"fileid": "d524986e-7740-3295-8152-6b32a12c5fa4",
				"height": 1280,
				"width": 1280,
				"url": "http://ci.xiaohongshu.com/d524986e-7740-3295-8152-6b32a12c5fa4?imageView2/2/w/540/format/jpg",
				"original": "http://ci.xiaohongshu.com/d524986e-7740-3295-8152-6b32a12c5fa4",
				"index": 0,
				"url_size_large": "http://ci.xiaohongshu.com/d524986e-7740-3295-8152-6b32a12c5fa4?imageView2/2/w/1080/format/jpg"
			}, {
				"fileid": "d9b216a5-3c99-3b63-89ac-aafaeeb61920",
				"height": 1280,
				"width": 1280,
				"url": "http://ci.xiaohongshu.com/d9b216a5-3c99-3b63-89ac-aafaeeb61920?imageView2/2/w/540/format/jpg",
				"original": "http://ci.xiaohongshu.com/d9b216a5-3c99-3b63-89ac-aafaeeb61920",
				"url_size_large": "http://ci.xiaohongshu.com/d9b216a5-3c99-3b63-89ac-aafaeeb61920?imageView2/2/w/1080/format/jpg"
			}, {
				"fileid": "a6a1852e-5eb2-33e5-826a-36059edfb266",
				"height": 1280,
				"width": 1280,
				"url": "http://ci.xiaohongshu.com/a6a1852e-5eb2-33e5-826a-36059edfb266?imageView2/2/w/540/format/jpg",
				"original": "http://ci.xiaohongshu.com/a6a1852e-5eb2-33e5-826a-36059edfb266",
				"url_size_large": "http://ci.xiaohongshu.com/a6a1852e-5eb2-33e5-826a-36059edfb266?imageView2/2/w/1080/format/jpg"
			}, {
				"fileid": "e6da45fa-b0ed-3504-a2d7-4f4e1f539834",
				"height": 1280,
				"width": 1280,
				"url": "http://ci.xiaohongshu.com/e6da45fa-b0ed-3504-a2d7-4f4e1f539834?imageView2/2/w/540/format/jpg",
				"original": "http://ci.xiaohongshu.com/e6da45fa-b0ed-3504-a2d7-4f4e1f539834",
				"url_size_large": "http://ci.xiaohongshu.com/e6da45fa-b0ed-3504-a2d7-4f4e1f539834?imageView2/2/w/1080/format/jpg"
			}, {
				"fileid": "85f8c377-5f32-3b55-8b23-d7ecf745abf5",
				"height": 1079,
				"width": 1080,
				"url": "http://ci.xiaohongshu.com/85f8c377-5f32-3b55-8b23-d7ecf745abf5?imageView2/2/h/540/format/jpg",
				"original": "http://ci.xiaohongshu.com/85f8c377-5f32-3b55-8b23-d7ecf745abf5",
				"url_size_large": "http://ci.xiaohongshu.com/85f8c377-5f32-3b55-8b23-d7ecf745abf5?imageView2/2/h/1080/format/jpg"
			}],
			"is_ads": false
		}, {
			"liked": false,
			"id": "5cfc8b090000000027007e68",
			"title": "口红涂法示范4⃣️雾面唇釉\uD83E\uDD23含抿嘴大法",
			"desc": "VCND 104 前置无滤镜口红试色\uD83D\uDC84 . ✨BGM：Sad Forever 大噶好！猝不及防的更新！口红涂法最新一期",
			"type": "video",
			"user": {
				"images": "https://img.xiaohongshu.com/avatar/5c345de0692cf800017ade7a.jpg@80w_80h_90q_1e_1c_1x.jpg",
				"nickname": "是红字呀",
				"red_official_verified": false,
				"red_official_verify_type": 0,
				"userid": "58ddd86350c4b40cf465e5dd"
			},
			"video_info": {
				"id": "5cfc8b09329fad0001c95ced",
				"height": 1280,
				"width": 720,
				"url": "http://v.xiaohongshu.com/085cc167cf74c0cd0072ed1836c43bf3cbe00228?sign=60267abfe3efd2be3bce99f88d45415c&t=5d10f380",
				"gif_url": "http://sg.xiaohongshu.com/lvpSUQA-ZJVMvZFtmaT2PQe1J19t_gif_w320?imageView2/0/format/webp",
				"preload_size": 1048576,
				"played_count": 292600
			},
			"image_info": {
				"fileid": "1246855d-5cfd-3f04-9a36-a0c38d8ece22",
				"height": 1280,
				"width": 720,
				"url": "http://ci.xiaohongshu.com/1246855d-5cfd-3f04-9a36-a0c38d8ece22?imageView2/2/w/540/format/jpg",
				"original": "http://ci.xiaohongshu.com/1246855d-5cfd-3f04-9a36-a0c38d8ece22",
				"index": 0,
				"url_size_large": "http://ci.xiaohongshu.com/1246855d-5cfd-3f04-9a36-a0c38d8ece22?imageView2/2/w/1080/format/jpg"
			},
			"liked_count": 6063,
			"tag_info": {},
			"images_list": [{
				"fileid": "1246855d-5cfd-3f04-9a36-a0c38d8ece22",
				"height": 1280,
				"width": 720,
				"url": "http://ci.xiaohongshu.com/1246855d-5cfd-3f04-9a36-a0c38d8ece22?imageView2/2/w/540/format/jpg",
				"original": "http://ci.xiaohongshu.com/1246855d-5cfd-3f04-9a36-a0c38d8ece22",
				"index": 0,
				"url_size_large": "http://ci.xiaohongshu.com/1246855d-5cfd-3f04-9a36-a0c38d8ece22?imageView2/2/w/1080/format/jpg"
			}],
			"is_ads": false
		}, {
			"title": "",
			"desc": "",
			"is_ads": true,
			"ads_info": {
				"ads_id": "133280",
				"track_id": "adscpcg_b8d64089-934f-11e9-bce5-52540018ffb6@c83568158a134f08a3118c37dfaa03b5",
				"show_tag": true,
				"is_banner": false,
				"banner_info": {
					"desc": ""
				},
				"trackPos": 1,
				"is_goods": true,
				"goods_info": {
					"title": "中国·雕花定制款",
					"desc": "Florasis花西子 花隐星穹雕花口红 M116彤心绣（烂番茄色）",
					"id": "5ce89aa16a5138002c1617d3",
					"link": "xhsdiscover://webview/www.xiaohongshu.com/goods/5ce89aa16a5138002c1617d3?isRN=true&rnName=fantasy-goods-detail-rn&rnPath=goods/5ce89aa16a5138002c1617d3",
					"tags": [],
					"image_info": {
						"url": "https://qimg.xiaohongshu.com/0b033120-7e9b-11e9-8395-49f288055593?imageView2/1/w/320/h/427/q/90.jpg",
						"height": 427,
						"width": 320
					},
					"item_price": [{
						"type": "sale_price",
						"price": 129.0,
						"index": 1
					}, {
						"type": "origin_price",
						"price": 129.9,
						"index": 3
					}],
					"vendor_icon": "http://img.xiaohongshu.com/seller/fc6a5576eaff79ca61d909b9aaa78c7a"
				}
			}
		}, {
			"liked": false,
			"id": "5ce91e7c000000000f025d8b",
			"title": "Colourpop星星口红新色\uD83D\uDE2D21 Questions天啊",
			"desc": "附colorpop Foolish、Better Off对比 卡乐泡泡 前置无滤镜口红试色\uD83D\uDC84 . ✨BGM：晚安 对不",
			"type": "video",
			"user": {
				"images": "https://img.xiaohongshu.com/avatar/5c345de0692cf800017ade7a.jpg@80w_80h_90q_1e_1c_1x.jpg",
				"nickname": "是红字呀",
				"red_official_verified": false,
				"red_official_verify_type": 0,
				"userid": "58ddd86350c4b40cf465e5dd"
			},
			"video_info": {
				"id": "5ce91e7c1f970900012b4a15",
				"height": 1280,
				"width": 720,
				"url": "http://v.xiaohongshu.com/14a5486f1891a0f9c8a63fdc427c75b375e352ce?sign=ad120be55ad7b5ebb0656a2c81e375e6&t=5d10f380",
				"gif_url": "http://sg.xiaohongshu.com/lo3TeKXQ55-8NGB7zieKWGl9zPnH_gif_w320?imageView2/0/format/webp",
				"preload_size": 1048576,
				"played_count": 149800
			},
			"image_info": {
				"fileid": "8cfb1167-34fa-5f55-b6c5-a836159d20a8",
				"height": 1280,
				"width": 720,
				"url": "http://ci.xiaohongshu.com/8cfb1167-34fa-5f55-b6c5-a836159d20a8?imageView2/2/w/540/format/jpg",
				"original": "http://ci.xiaohongshu.com/8cfb1167-34fa-5f55-b6c5-a836159d20a8",
				"index": 0,
				"url_size_large": "http://ci.xiaohongshu.com/8cfb1167-34fa-5f55-b6c5-a836159d20a8?imageView2/2/w/1080/format/jpg"
			},
			"liked_count": 2684,
			"tag_info": {},
			"images_list": [{
				"fileid": "8cfb1167-34fa-5f55-b6c5-a836159d20a8",
				"height": 1280,
				"width": 720,
				"url": "http://ci.xiaohongshu.com/8cfb1167-34fa-5f55-b6c5-a836159d20a8?imageView2/2/w/540/format/jpg",
				"original": "http://ci.xiaohongshu.com/8cfb1167-34fa-5f55-b6c5-a836159d20a8",
				"index": 0,
				"url_size_large": "http://ci.xiaohongshu.com/8cfb1167-34fa-5f55-b6c5-a836159d20a8?imageView2/2/w/1080/format/jpg"
			}],
			"is_ads": false
		}, {
			"liked": false,
			"id": "5cfa153600000000280242a2",
			"title": "温柔豆沙色口红上线\uD83C\uDF67来一口甜甜绵绵冰吗！",
			"desc": "豆沙女孩\uD83D\uDC40过来～～巴卜又发现一只嘿嘿 \uD83E\uDDF8\uD83E\uDDF8\uD83E\uDDF8\uD83D\uDC95 色号是小星钻口红滴#rapunzel 豆沙粉 比较低饱和的一个",
			"type": "normal",
			"user": {
				"images": "https://img.xiaohongshu.com/avatar/5bc94385a2f5280001119d01.jpg@80w_80h_90q_1e_1c_1x.jpg",
				"nickname": "凯仪王bubble",
				"red_official_verified": false,
				"red_official_verify_type": 0,
				"userid": "5880bf4550c4b46c6c84feaa"
			},
			"image_info": {
				"fileid": "9986701f-ba7f-3b95-8636-555a88342807",
				"height": 1280,
				"width": 960,
				"url": "http://ci.xiaohongshu.com/9986701f-ba7f-3b95-8636-555a88342807?imageView2/2/w/540/format/jpg",
				"original": "http://ci.xiaohongshu.com/9986701f-ba7f-3b95-8636-555a88342807",
				"index": 0,
				"url_size_large": "http://ci.xiaohongshu.com/9986701f-ba7f-3b95-8636-555a88342807?imageView2/2/w/1080/format/jpg"
			},
			"liked_count": 1328,
			"tag_info": {},
			"images_list": [{
				"fileid": "9986701f-ba7f-3b95-8636-555a88342807",
				"height": 1280,
				"width": 960,
				"url": "http://ci.xiaohongshu.com/9986701f-ba7f-3b95-8636-555a88342807?imageView2/2/w/540/format/jpg",
				"original": "http://ci.xiaohongshu.com/9986701f-ba7f-3b95-8636-555a88342807",
				"index": 0,
				"url_size_large": "http://ci.xiaohongshu.com/9986701f-ba7f-3b95-8636-555a88342807?imageView2/2/w/1080/format/jpg"
			}, {
				"fileid": "ceea3a90-398f-3a9c-96d4-8a2669a65ec6",
				"height": 1280,
				"width": 960,
				"url": "http://ci.xiaohongshu.com/ceea3a90-398f-3a9c-96d4-8a2669a65ec6?imageView2/2/w/540/format/jpg",
				"original": "http://ci.xiaohongshu.com/ceea3a90-398f-3a9c-96d4-8a2669a65ec6",
				"url_size_large": "http://ci.xiaohongshu.com/ceea3a90-398f-3a9c-96d4-8a2669a65ec6?imageView2/2/w/1080/format/jpg"
			}, {
				"fileid": "6efba7b6-f1ec-3d7b-a0b2-d46721a4a2a9",
				"height": 1280,
				"width": 960,
				"url": "http://ci.xiaohongshu.com/6efba7b6-f1ec-3d7b-a0b2-d46721a4a2a9?imageView2/2/w/540/format/jpg",
				"original": "http://ci.xiaohongshu.com/6efba7b6-f1ec-3d7b-a0b2-d46721a4a2a9",
				"url_size_large": "http://ci.xiaohongshu.com/6efba7b6-f1ec-3d7b-a0b2-d46721a4a2a9?imageView2/2/w/1080/format/jpg"
			}, {
				"fileid": "27a59a50-db46-3b72-8e48-2cbdea1d71a8",
				"height": 1280,
				"width": 960,
				"url": "http://ci.xiaohongshu.com/27a59a50-db46-3b72-8e48-2cbdea1d71a8?imageView2/2/w/540/format/jpg",
				"original": "http://ci.xiaohongshu.com/27a59a50-db46-3b72-8e48-2cbdea1d71a8",
				"url_size_large": "http://ci.xiaohongshu.com/27a59a50-db46-3b72-8e48-2cbdea1d71a8?imageView2/2/w/1080/format/jpg"
			}, {
				"fileid": "f9128702-6cc3-33d6-a1dd-b620212ee0ff",
				"height": 1280,
				"width": 959,
				"url": "http://ci.xiaohongshu.com/f9128702-6cc3-33d6-a1dd-b620212ee0ff?imageView2/2/w/540/format/jpg",
				"original": "http://ci.xiaohongshu.com/f9128702-6cc3-33d6-a1dd-b620212ee0ff",
				"url_size_large": "http://ci.xiaohongshu.com/f9128702-6cc3-33d6-a1dd-b620212ee0ff?imageView2/2/w/1080/format/jpg"
			}, {
				"fileid": "b4c1b2e4-1c36-3666-86c4-c640dc23427d",
				"height": 1280,
				"width": 960,
				"url": "http://ci.xiaohongshu.com/b4c1b2e4-1c36-3666-86c4-c640dc23427d?imageView2/2/w/540/format/jpg",
				"original": "http://ci.xiaohongshu.com/b4c1b2e4-1c36-3666-86c4-c640dc23427d",
				"url_size_large": "http://ci.xiaohongshu.com/b4c1b2e4-1c36-3666-86c4-c640dc23427d?imageView2/2/w/1080/format/jpg"
			}, {
				"fileid": "81e6ae5c-e7a9-35e5-8cbf-68488f719b9e",
				"height": 1280,
				"width": 960,
				"url": "http://ci.xiaohongshu.com/81e6ae5c-e7a9-35e5-8cbf-68488f719b9e?imageView2/2/w/540/format/jpg",
				"original": "http://ci.xiaohongshu.com/81e6ae5c-e7a9-35e5-8cbf-68488f719b9e",
				"url_size_large": "http://ci.xiaohongshu.com/81e6ae5c-e7a9-35e5-8cbf-68488f719b9e?imageView2/2/w/1080/format/jpg"
			}],
			"is_ads": false
		}, {
			"liked": false,
			"id": "5cf74303000000002601a615",
			"title": "Ysl热门色号对比试色❗️9只热门口红试色❗️",
			"desc": "之前出了2019ysl夏季限定新色425和424，有好多宝宝问我跟各种口红颜色像不像？问的宝宝比较多我就干脆出个对比试色",
			"type": "normal",
			"user": {
				"images": "https://img.xiaohongshu.com/avatar/5b780a7bf5de7b00011d855e.jpg@80w_80h_90q_1e_1c_1x.jpg",
				"nickname": "Pink_pink",
				"red_official_verified": false,
				"red_official_verify_type": 0,
				"userid": "5a9a6cfbe8ac2b490e7cef81"
			},
			"image_info": {
				"fileid": "dd1cdaed-225d-3d72-9017-ec6a3c265e9d",
				"height": 1280,
				"width": 960,
				"url": "http://ci.xiaohongshu.com/dd1cdaed-225d-3d72-9017-ec6a3c265e9d?imageView2/2/w/540/format/jpg",
				"original": "http://ci.xiaohongshu.com/dd1cdaed-225d-3d72-9017-ec6a3c265e9d",
				"index": 0,
				"url_size_large": "http://ci.xiaohongshu.com/dd1cdaed-225d-3d72-9017-ec6a3c265e9d?imageView2/2/w/1080/format/jpg"
			},
			"liked_count": 2703,
			"tag_info": {},
			"images_list": [{
				"fileid": "dd1cdaed-225d-3d72-9017-ec6a3c265e9d",
				"height": 1280,
				"width": 960,
				"url": "http://ci.xiaohongshu.com/dd1cdaed-225d-3d72-9017-ec6a3c265e9d?imageView2/2/w/540/format/jpg",
				"original": "http://ci.xiaohongshu.com/dd1cdaed-225d-3d72-9017-ec6a3c265e9d",
				"index": 0,
				"url_size_large": "http://ci.xiaohongshu.com/dd1cdaed-225d-3d72-9017-ec6a3c265e9d?imageView2/2/w/1080/format/jpg"
			}, {
				"fileid": "764e8698-f982-393b-a5bc-b954e696e830",
				"height": 1280,
				"width": 961,
				"url": "http://ci.xiaohongshu.com/764e8698-f982-393b-a5bc-b954e696e830?imageView2/2/w/540/format/jpg",
				"original": "http://ci.xiaohongshu.com/764e8698-f982-393b-a5bc-b954e696e830",
				"url_size_large": "http://ci.xiaohongshu.com/764e8698-f982-393b-a5bc-b954e696e830?imageView2/2/w/1080/format/jpg"
			}, {
				"fileid": "35e0dddc-e663-39e2-a403-baab347f829a",
				"height": 1280,
				"width": 959,
				"url": "http://ci.xiaohongshu.com/35e0dddc-e663-39e2-a403-baab347f829a?imageView2/2/w/540/format/jpg",
				"original": "http://ci.xiaohongshu.com/35e0dddc-e663-39e2-a403-baab347f829a",
				"url_size_large": "http://ci.xiaohongshu.com/35e0dddc-e663-39e2-a403-baab347f829a?imageView2/2/w/1080/format/jpg"
			}, {
				"fileid": "e4d0a876-6849-3ac9-bb25-10ce59637bb9",
				"height": 1280,
				"width": 961,
				"url": "http://ci.xiaohongshu.com/e4d0a876-6849-3ac9-bb25-10ce59637bb9?imageView2/2/w/540/format/jpg",
				"original": "http://ci.xiaohongshu.com/e4d0a876-6849-3ac9-bb25-10ce59637bb9",
				"url_size_large": "http://ci.xiaohongshu.com/e4d0a876-6849-3ac9-bb25-10ce59637bb9?imageView2/2/w/1080/format/jpg"
			}, {
				"fileid": "3561981e-4e1c-3437-bb14-f0586729b833",
				"height": 1280,
				"width": 961,
				"url": "http://ci.xiaohongshu.com/3561981e-4e1c-3437-bb14-f0586729b833?imageView2/2/w/540/format/jpg",
				"original": "http://ci.xiaohongshu.com/3561981e-4e1c-3437-bb14-f0586729b833",
				"url_size_large": "http://ci.xiaohongshu.com/3561981e-4e1c-3437-bb14-f0586729b833?imageView2/2/w/1080/format/jpg"
			}, {
				"fileid": "faa6bf7b-0017-3082-91b9-528317b8fa7d",
				"height": 1280,
				"width": 959,
				"url": "http://ci.xiaohongshu.com/faa6bf7b-0017-3082-91b9-528317b8fa7d?imageView2/2/w/540/format/jpg",
				"original": "http://ci.xiaohongshu.com/faa6bf7b-0017-3082-91b9-528317b8fa7d",
				"url_size_large": "http://ci.xiaohongshu.com/faa6bf7b-0017-3082-91b9-528317b8fa7d?imageView2/2/w/1080/format/jpg"
			}, {
				"fileid": "9c631596-b484-3ec2-af1d-4019e76410d4",
				"height": 1280,
				"width": 961,
				"url": "http://ci.xiaohongshu.com/9c631596-b484-3ec2-af1d-4019e76410d4?imageView2/2/w/540/format/jpg",
				"original": "http://ci.xiaohongshu.com/9c631596-b484-3ec2-af1d-4019e76410d4",
				"url_size_large": "http://ci.xiaohongshu.com/9c631596-b484-3ec2-af1d-4019e76410d4?imageView2/2/w/1080/format/jpg"
			}, {
				"fileid": "46acf8ec-55b0-35c5-88eb-fcc97dfa4eba",
				"height": 1280,
				"width": 959,
				"url": "http://ci.xiaohongshu.com/46acf8ec-55b0-35c5-88eb-fcc97dfa4eba?imageView2/2/w/540/format/jpg",
				"original": "http://ci.xiaohongshu.com/46acf8ec-55b0-35c5-88eb-fcc97dfa4eba",
				"url_size_large": "http://ci.xiaohongshu.com/46acf8ec-55b0-35c5-88eb-fcc97dfa4eba?imageView2/2/w/1080/format/jpg"
			}, {
				"fileid": "723cdd8d-ac7f-392b-a9cc-05262fb5b335",
				"height": 1280,
				"width": 960,
				"url": "http://ci.xiaohongshu.com/723cdd8d-ac7f-392b-a9cc-05262fb5b335?imageView2/2/w/540/format/jpg",
				"original": "http://ci.xiaohongshu.com/723cdd8d-ac7f-392b-a9cc-05262fb5b335",
				"url_size_large": "http://ci.xiaohongshu.com/723cdd8d-ac7f-392b-a9cc-05262fb5b335?imageView2/2/w/1080/format/jpg"
			}],
			"is_ads": false
		}, {
			"liked": false,
			"id": "5cb85205000000000e006236",
			"title": "",
			"desc": "必须拥有的十支回购口红，你有多少支？ 个人爱好口红，家里真的一堆杂七杂八的口红，直接分享使用过就觉得必须分享的十款最爱口",
			"type": "normal",
			"user": {
				"images": "https://img.xiaohongshu.com/avatar/5c107c280a974100017ff69c.jpg@80w_80h_90q_1e_1c_1x.jpg",
				"nickname": "妆妆小姐\uD83D\uDC8B",
				"red_official_verified": false,
				"red_official_verify_type": 0,
				"userid": "5b754f98c8f9b40001865cba"
			},
			"image_info": {
				"fileid": "68615b43-697b-5a52-9170-496c1379ffcd",
				"height": 1280,
				"width": 959,
				"url": "http://ci.xiaohongshu.com/68615b43-697b-5a52-9170-496c1379ffcd?imageView2/2/w/540/format/jpg",
				"original": "http://ci.xiaohongshu.com/68615b43-697b-5a52-9170-496c1379ffcd",
				"index": 0,
				"url_size_large": "http://ci.xiaohongshu.com/68615b43-697b-5a52-9170-496c1379ffcd?imageView2/2/w/1080/format/jpg"
			},
			"liked_count": 27974,
			"tag_info": {},
			"images_list": [{
				"fileid": "68615b43-697b-5a52-9170-496c1379ffcd",
				"height": 1280,
				"width": 959,
				"url": "http://ci.xiaohongshu.com/68615b43-697b-5a52-9170-496c1379ffcd?imageView2/2/w/540/format/jpg",
				"original": "http://ci.xiaohongshu.com/68615b43-697b-5a52-9170-496c1379ffcd",
				"index": 0,
				"url_size_large": "http://ci.xiaohongshu.com/68615b43-697b-5a52-9170-496c1379ffcd?imageView2/2/w/1080/format/jpg"
			}, {
				"fileid": "44ee7dcc-6ef8-55cb-82c9-1b3d45d2b221",
				"height": 1280,
				"width": 959,
				"url": "http://ci.xiaohongshu.com/44ee7dcc-6ef8-55cb-82c9-1b3d45d2b221?imageView2/2/w/540/format/jpg",
				"original": "http://ci.xiaohongshu.com/44ee7dcc-6ef8-55cb-82c9-1b3d45d2b221",
				"url_size_large": "http://ci.xiaohongshu.com/44ee7dcc-6ef8-55cb-82c9-1b3d45d2b221?imageView2/2/w/1080/format/jpg"
			}, {
				"fileid": "36d874bb-672a-595b-8b17-8ad7a7d28fd5",
				"height": 1280,
				"width": 959,
				"url": "http://ci.xiaohongshu.com/36d874bb-672a-595b-8b17-8ad7a7d28fd5?imageView2/2/w/540/format/jpg",
				"original": "http://ci.xiaohongshu.com/36d874bb-672a-595b-8b17-8ad7a7d28fd5",
				"url_size_large": "http://ci.xiaohongshu.com/36d874bb-672a-595b-8b17-8ad7a7d28fd5?imageView2/2/w/1080/format/jpg"
			}, {
				"fileid": "446a51a7-bd8e-58ca-961f-1f7a75449274",
				"height": 1280,
				"width": 959,
				"url": "http://ci.xiaohongshu.com/446a51a7-bd8e-58ca-961f-1f7a75449274?imageView2/2/w/540/format/jpg",
				"original": "http://ci.xiaohongshu.com/446a51a7-bd8e-58ca-961f-1f7a75449274",
				"url_size_large": "http://ci.xiaohongshu.com/446a51a7-bd8e-58ca-961f-1f7a75449274?imageView2/2/w/1080/format/jpg"
			}, {
				"fileid": "d54e7f8b-75e0-5453-b3a1-e8329bf158e9",
				"height": 1280,
				"width": 959,
				"url": "http://ci.xiaohongshu.com/d54e7f8b-75e0-5453-b3a1-e8329bf158e9?imageView2/2/w/540/format/jpg",
				"original": "http://ci.xiaohongshu.com/d54e7f8b-75e0-5453-b3a1-e8329bf158e9",
				"url_size_large": "http://ci.xiaohongshu.com/d54e7f8b-75e0-5453-b3a1-e8329bf158e9?imageView2/2/w/1080/format/jpg"
			}, {
				"fileid": "0eac36d5-3735-5544-a16b-3cd84baf6551",
				"height": 1280,
				"width": 959,
				"url": "http://ci.xiaohongshu.com/0eac36d5-3735-5544-a16b-3cd84baf6551?imageView2/2/w/540/format/jpg",
				"original": "http://ci.xiaohongshu.com/0eac36d5-3735-5544-a16b-3cd84baf6551",
				"url_size_large": "http://ci.xiaohongshu.com/0eac36d5-3735-5544-a16b-3cd84baf6551?imageView2/2/w/1080/format/jpg"
			}],
			"is_ads": false
		}, {
			"liked": false,
			"id": "5d04baaa0000000026036d3b",
			"title": "植村秀今年开挂了‼️连着入了3只口红\uD83D\uDC84美腻",
			"desc": "不专业美妆博主又来肉雯 又来分享新买的口红了哈哈哈哈 最近都没怎么好好拍照\uD83D\uDCF7但最近随便发发的笔记好像也没受到你们的冷落",
			"type": "normal",
			"user": {
				"images": "https://img.xiaohongshu.com/avatar/5d01c2e5b12afe000122564a.jpg@80w_80h_90q_1e_1c_1x.jpg",
				"nickname": "肉雯",
				"red_official_verified": false,
				"red_official_verify_type": 0,
				"userid": "58cd59bb50c4b42d2e7d8073"
			},
			"image_info": {
				"fileid": "a781fcde-8a5d-3517-88d5-85e102559fe7",
				"height": 1706,
				"width": 1280,
				"url": "http://ci.xiaohongshu.com/a781fcde-8a5d-3517-88d5-85e102559fe7?imageView2/2/w/540/format/jpg",
				"original": "http://ci.xiaohongshu.com/a781fcde-8a5d-3517-88d5-85e102559fe7",
				"index": 0,
				"url_size_large": "http://ci.xiaohongshu.com/a781fcde-8a5d-3517-88d5-85e102559fe7?imageView2/2/w/1080/format/jpg"
			},
			"liked_count": 3209,
			"tag_info": {},
			"images_list": [{
				"fileid": "a781fcde-8a5d-3517-88d5-85e102559fe7",
				"height": 1706,
				"width": 1280,
				"url": "http://ci.xiaohongshu.com/a781fcde-8a5d-3517-88d5-85e102559fe7?imageView2/2/w/540/format/jpg",
				"original": "http://ci.xiaohongshu.com/a781fcde-8a5d-3517-88d5-85e102559fe7",
				"index": 0,
				"url_size_large": "http://ci.xiaohongshu.com/a781fcde-8a5d-3517-88d5-85e102559fe7?imageView2/2/w/1080/format/jpg"
			}, {
				"fileid": "23600b1c-ca94-39c6-aa52-d4a000faddcb",
				"height": 1706,
				"width": 1280,
				"url": "http://ci.xiaohongshu.com/23600b1c-ca94-39c6-aa52-d4a000faddcb?imageView2/2/w/540/format/jpg",
				"original": "http://ci.xiaohongshu.com/23600b1c-ca94-39c6-aa52-d4a000faddcb",
				"url_size_large": "http://ci.xiaohongshu.com/23600b1c-ca94-39c6-aa52-d4a000faddcb?imageView2/2/w/1080/format/jpg"
			}, {
				"fileid": "6ea88d3b-3e57-33b2-ab1b-5b9dbed622a3",
				"height": 1706,
				"width": 1280,
				"url": "http://ci.xiaohongshu.com/6ea88d3b-3e57-33b2-ab1b-5b9dbed622a3?imageView2/2/w/540/format/jpg",
				"original": "http://ci.xiaohongshu.com/6ea88d3b-3e57-33b2-ab1b-5b9dbed622a3",
				"url_size_large": "http://ci.xiaohongshu.com/6ea88d3b-3e57-33b2-ab1b-5b9dbed622a3?imageView2/2/w/1080/format/jpg"
			}, {
				"fileid": "b1970001-a82e-3b35-af40-413dc7b033b2",
				"height": 1706,
				"width": 1280,
				"url": "http://ci.xiaohongshu.com/b1970001-a82e-3b35-af40-413dc7b033b2?imageView2/2/w/540/format/jpg",
				"original": "http://ci.xiaohongshu.com/b1970001-a82e-3b35-af40-413dc7b033b2",
				"url_size_large": "http://ci.xiaohongshu.com/b1970001-a82e-3b35-af40-413dc7b033b2?imageView2/2/w/1080/format/jpg"
			}, {
				"fileid": "b22c3b9d-7073-317b-9a3a-7f4e87fe1007",
				"height": 1706,
				"width": 1280,
				"url": "http://ci.xiaohongshu.com/b22c3b9d-7073-317b-9a3a-7f4e87fe1007?imageView2/2/w/540/format/jpg",
				"original": "http://ci.xiaohongshu.com/b22c3b9d-7073-317b-9a3a-7f4e87fe1007",
				"url_size_large": "http://ci.xiaohongshu.com/b22c3b9d-7073-317b-9a3a-7f4e87fe1007?imageView2/2/w/1080/format/jpg"
			}, {
				"fileid": "2ab6e04b-e869-35cf-a633-11b7948f7999",
				"height": 1706,
				"width": 1280,
				"url": "http://ci.xiaohongshu.com/2ab6e04b-e869-35cf-a633-11b7948f7999?imageView2/2/w/540/format/jpg",
				"original": "http://ci.xiaohongshu.com/2ab6e04b-e869-35cf-a633-11b7948f7999",
				"url_size_large": "http://ci.xiaohongshu.com/2ab6e04b-e869-35cf-a633-11b7948f7999?imageView2/2/w/1080/format/jpg"
			}, {
				"fileid": "357a3dbd-26af-3b00-bb47-ae9326fef397",
				"height": 1706,
				"width": 1280,
				"url": "http://ci.xiaohongshu.com/357a3dbd-26af-3b00-bb47-ae9326fef397?imageView2/2/w/540/format/jpg",
				"original": "http://ci.xiaohongshu.com/357a3dbd-26af-3b00-bb47-ae9326fef397",
				"url_size_large": "http://ci.xiaohongshu.com/357a3dbd-26af-3b00-bb47-ae9326fef397?imageView2/2/w/1080/format/jpg"
			}],
			"is_ads": false
		}],
		"total_count": -1,
		"recommend_query": {
			"position": 43,
			"queries": [{
				"name": "阿玛尼",
				"id": "阿玛尼"
			}, {
				"name": "ysl",
				"id": "ysl"
			}, {
				"name": "tf",
				"id": "tf"
			}, {
				"name": "阿玛尼405",
				"id": "阿玛尼405"
			}, {
				"name": "娇兰口红",
				"id": "娇兰口红"
			}, {
				"name": "平价口红",
				"id": "平价口红"
			}, {
				"name": "眼影",
				"id": "眼影"
			}, {
				"name": "香奈儿",
				"id": "香奈儿"
			}]
		},
		"recommend_info": {},
		"recommend_notes": []
	}
}